[
  {
    "full_name": "gothinkster/realworld",
    "stargazers_count": 66919,
    "open_issues_count": 56,
    "forks_count": 6200
  },
  {
    "full_name": "CRED-CLUB/neopop-web",
    "stargazers_count": 601,
    "open_issues_count": 5,
    "forks_count": 88
  },
  {
    "full_name": "kamranahmedse/developer-roadmap",
    "stargazers_count": 199966,
    "open_issues_count": 164,
    "forks_count": 28576
  },
  {
    "full_name": "Unitech/pm2",
    "stargazers_count": 37320,
    "open_issues_count": 618,
    "forks_count": 2441
  },
  {
    "full_name": "do-community/do-article-templates",
    "stargazers_count": 123,
    "open_issues_count": 2,
    "forks_count": 77
  },
  {
    "full_name": "hoppscotch/hoppscotch",
    "stargazers_count": 44852,
    "open_issues_count": 88,
    "forks_count": 3032
  },
  {
    "full_name": "kelektiv/node-cron",
    "stargazers_count": 7464,
    "open_issues_count": 120,
    "forks_count": 591
  },
  {
    "full_name": "PatrickJS/awesome-angular",
    "stargazers_count": 8385,
    "open_issues_count": 5,
    "forks_count": 1259
  },
  {
    "full_name": "prinick96/hex-arch-go",
    "stargazers_count": 12,
    "open_issues_count": 0,
    "forks_count": 0
  },
  {
    "full_name": "RivuChk/Jetpack-Compose-MVI-Demo",
    "stargazers_count": 135,
    "open_issues_count": 0,
    "forks_count": 20
  },
  {
    "full_name": "localstack/localstack",
    "stargazers_count": 41984,
    "open_issues_count": 353,
    "forks_count": 3121
  },
  {
    "full_name": "aws-quickstart/quickstart-amazon-eks",
    "stargazers_count": 379,
    "open_issues_count": 75,
    "forks_count": 336
  },
  {
    "full_name": "geshan/nodejs-posgresql",
    "stargazers_count": 57,
    "open_issues_count": 0,
    "forks_count": 190
  },
  {
    "full_name": "InterviewReady/system-design-resources",
    "stargazers_count": 6145,
    "open_issues_count": 1,
    "forks_count": 692
  },
  {
    "full_name": "apple/swift",
    "stargazers_count": 60039,
    "open_issues_count": 5998,
    "forks_count": 9661
  },
  {
    "full_name": "hitherejoe/ComposeAcademy-Playground",
    "stargazers_count": 827,
    "open_issues_count": 2,
    "forks_count": 77
  },
  {
    "full_name": "fluxcd/flux2",
    "stargazers_count": 3535,
    "open_issues_count": 142,
    "forks_count": 376
  },
  {
    "full_name": "andrewbaisden/complete-react-developer",
    "stargazers_count": 11,
    "open_issues_count": 0,
    "forks_count": 5
  },
  {
    "full_name": "nvm-sh/nvm",
    "stargazers_count": 59194,
    "open_issues_count": 360,
    "forks_count": 6285
  },
  {
    "full_name": "donnemartin/stocks",
    "stargazers_count": 56,
    "open_issues_count": 0,
    "forks_count": 31
  },
  {
    "full_name": "donnemartin/dev-setup",
    "stargazers_count": 5759,
    "open_issues_count": 33,
    "forks_count": 1127
  },
  {
    "full_name": "donnemartin/system-design-primer",
    "stargazers_count": 187245,
    "open_issues_count": 318,
    "forks_count": 34019
  },
  {
    "full_name": "android/nowinandroid",
    "stargazers_count": 5505,
    "open_issues_count": 32,
    "forks_count": 516
  },
  {
    "full_name": "kudoabhijeet/url-shortener",
    "stargazers_count": 1,
    "open_issues_count": 0,
    "forks_count": 0
  },
  {
    "full_name": "qurbat/upi-recon",
    "stargazers_count": 55,
    "open_issues_count": 6,
    "forks_count": 12
  },
  {
    "full_name": "PhilippeBoisney/ArchApp",
    "stargazers_count": 595,
    "open_issues_count": 6,
    "forks_count": 99
  },
  {
    "full_name": "markmead/hyperui",
    "stargazers_count": 2536,
    "open_issues_count": 1,
    "forks_count": 98
  },
  {
    "full_name": "pyscript/pyscript",
    "stargazers_count": 13707,
    "open_issues_count": 168,
    "forks_count": 957
  },
  {
    "full_name": "education/GitHubGraduation-2022",
    "stargazers_count": 1421,
    "open_issues_count": 547,
    "forks_count": 6646
  },
  {
    "full_name": "printezisn/spring-boot-microservices-starter",
    "stargazers_count": 22,
    "open_issues_count": 11,
    "forks_count": 1
  }
]